.gitignore
editdistance-0.8.0.dist-info/WHEEL
editdistance-0.8.0.dist-info/RECORD
editdistance-0.8.0.dist-info/METADATA
editdistance-0.8.0.dist-info/licenses/LICENSE
editdistance/bycython.pyx
editdistance/__init__.pxd
editdistance/_editdistance.h
editdistance/bycython.pxd
editdistance/_editdistance.cpp
editdistance/bycython.cpp
editdistance/bycython.pypy39-pp73-x86_64-linux-gnu.so
editdistance/__init__.py
editdistance/def.h
