Metadata-Version: 2.1
Name: editdistance
Version: 0.8.0
Summary: Default template for PDM package
Author-Email: Hiroyuki Tanaka <aflc0x@gmail.com>
License: MIT
Requires-Python: >=3.8
